starpicker/__init__.py
starpicker/collectors.py
starpicker/config.py
starpicker/reviews.py
starpicker/run.py
starpicker-0.5.1.dist-info/DESCRIPTION.rst
starpicker-0.5.1.dist-info/METADATA
starpicker-0.5.1.dist-info/RECORD
starpicker-0.5.1.dist-info/WHEEL
starpicker-0.5.1.dist-info/entry_points.txt
starpicker-0.5.1.dist-info/metadata.json
starpicker-0.5.1.dist-info/top_level.txt
