Metadata-Version: 2.0
Name: starpicker
Version: 0.5.1
Summary: A tool that periodically checks sites for feedback about an entity and posts the findings to Slack
Home-page: https://github.com/skypicker/starpicker
Author: Bence Nagy
Author-email: bence@skypicker.com
License: UNKNOWN
Download-URL: https://github.com/skypicker/starpicker/releases
Platform: UNKNOWN
Classifier: Development Status :: 4 - Beta
Classifier: Environment :: Console
Classifier: License :: OSI Approved :: GNU General Public License v2 (GPLv2)
Classifier: Operating System :: OS Independent
Classifier: Programming Language :: Python
Classifier: Programming Language :: Python :: 2
Classifier: Programming Language :: Python :: 2.7
Classifier: Programming Language :: Python :: 3
Classifier: Programming Language :: Python :: 3.5
Requires-Dist: beautifulsoup4 (<5)
Requires-Dist: redis (<3)
Requires-Dist: requests (<3)
Requires-Dist: textblob (<0.10)
